wofi.py
python_wofi-0.3.1.dist-info/licenses/LICENSE
python_wofi-0.3.1.dist-info/WHEEL
python_wofi-0.3.1.dist-info/METADATA
python_wofi-0.3.1.dist-info/RECORD
