Metadata-Version: 2.4
Name: python-wofi
Version: 0.3.1
Summary: Create simple GUIs using the Wofi application
Keywords: wofi
Author-email: Cristóbal Tapia Camú <crtapia@gmail.com>
Requires-Python: >=3.6
License-File: LICENSE
Project-URL: homepage, https://github.com/cristobaltapia/python-wofi
Project-URL: repository, https://github.com/cristobaltapia/python-wofi
